{"name":"NewFeatureType","type":"FeatureCollection"
,"features":[
{"type":"Feature","geometry":{"type":"Point","coordinates":[-85.6904116,42.9676265]},"properties":{"link":"https://navigator.er.usgs.gov/browse/node/1768457/history","NAME":"Michigan","node_id":1768457,"version":2}}
,{"type":"Feature","geometry":{"type":"Point","coordinates":[-85.7203071,42.9817158]},"properties":{"link":"https://navigator.er.usgs.gov/browse/node/1766902/history","NAME":"Michigan","node_id":1766902,"version":2}}
,{"type":"Feature","geometry":{"type":"Point","coordinates":[-85.6326157,42.9437919]},"properties":{"link":"https://navigator.er.usgs.gov/browse/node/1766134/history","NAME":"Michigan","node_id":1766134,"version":2}}
,{"type":"Feature","geometry":{"type":"Point","coordinates":[-85.7088625,42.9964632]},"properties":{"link":"https://navigator.er.usgs.gov/browse/node/1765699/history","NAME":"Michigan","node_id":1765699,"version":2}}
,{"type":"Feature","geometry":{"type":"Point","coordinates":[-85.6523269,42.9542318]},"properties":{"link":"https://navigator.er.usgs.gov/browse/node/1762770/history","NAME":"Michigan","node_id":1762770,"version":2}}
,{"type":"Feature","geometry":{"type":"Point","coordinates":[-85.6081511,42.9470228]},"properties":{"link":"https://navigator.er.usgs.gov/browse/node/1759572/history","NAME":"Michigan","node_id":1759572,"version":2}}
,{"type":"Feature","geometry":{"type":"Point","coordinates":[-85.7075401,42.9735447]},"properties":{"link":"https://navigator.er.usgs.gov/browse/node/1757345/history","NAME":"Michigan","node_id":1757345,"version":2}}
,{"type":"Feature","geometry":{"type":"Point","coordinates":[-85.6365235,42.9495869]},"properties":{"link":"https://navigator.er.usgs.gov/browse/node/1756951/history","NAME":"Michigan","node_id":1756951,"version":2}}
,{"type":"Feature","geometry":{"type":"Point","coordinates":[-85.6810034,42.9887679]},"properties":{"link":"https://navigator.er.usgs.gov/browse/node/1755152/history","NAME":"Michigan","node_id":1755152,"version":2}}
,{"type":"Feature","geometry":{"type":"Point","coordinates":[-85.6669225,42.9572169]},"properties":{"link":"https://navigator.er.usgs.gov/browse/node/1754768/history","NAME":"Michigan","node_id":1754768,"version":2}}
,{"type":"Feature","geometry":{"type":"Point","coordinates":[-85.7190012,42.9903795]},"properties":{"link":"https://navigator.er.usgs.gov/browse/node/1754568/history","NAME":"Michigan","node_id":1754568,"version":2}}
,{"type":"Feature","geometry":{"type":"Point","coordinates":[-85.7113861,42.9732404]},"properties":{"link":"https://navigator.er.usgs.gov/browse/node/1754449/history","NAME":"Michigan","node_id":1754449,"version":2}}
,{"type":"Feature","geometry":{"type":"Point","coordinates":[-85.7239955,42.9699697]},"properties":{"link":"https://navigator.er.usgs.gov/browse/node/1754105/history","NAME":"Michigan","node_id":1754105,"version":2}}
,{"type":"Feature","geometry":{"type":"Point","coordinates":[-85.6357455,42.9497635]},"properties":{"link":"https://navigator.er.usgs.gov/browse/node/1752523/history","NAME":"Michigan","node_id":1752523,"version":2}}
,{"type":"Feature","geometry":{"type":"Point","coordinates":[-85.70221,42.9861799]},"properties":{"link":"https://navigator.er.usgs.gov/browse/node/1750702/history","NAME":"Michigan","node_id":1750702,"version":2}}
,{"type":"Feature","geometry":{"type":"Point","coordinates":[-85.6322867,42.9435962]},"properties":{"link":"https://navigator.er.usgs.gov/browse/node/1750309/history","NAME":"Michigan","node_id":1750309,"version":2}}
,{"type":"Feature","geometry":{"type":"Point","coordinates":[-85.7313314,42.9956961]},"properties":{"link":"https://navigator.er.usgs.gov/browse/node/1749029/history","NAME":"Michigan","node_id":1749029,"version":2}}
,{"type":"Feature","geometry":{"type":"Point","coordinates":[-85.7229364,42.9810085]},"properties":{"link":"https://navigator.er.usgs.gov/browse/node/1747622/history","NAME":"Michigan","node_id":1747622,"version":2}}
,{"type":"Feature","geometry":{"type":"Point","coordinates":[-85.6662025,42.9579658]},"properties":{"link":"https://navigator.er.usgs.gov/browse/node/1747601/history","NAME":"Michigan","node_id":1747601,"version":2}}
,{"type":"Feature","geometry":{"type":"Point","coordinates":[-85.7276234,42.9852169]},"properties":{"link":"https://navigator.er.usgs.gov/browse/node/1746749/history","NAME":"Michigan","node_id":1746749,"version":2}}
,{"type":"Feature","geometry":{"type":"Point","coordinates":[-85.6139392,42.9489703]},"properties":{"link":"https://navigator.er.usgs.gov/browse/node/1746560/history","NAME":"Michigan","node_id":1746560,"version":2}}
,{"type":"Feature","geometry":{"type":"Point","coordinates":[-85.6192769,42.9512438]},"properties":{"link":"https://navigator.er.usgs.gov/browse/node/1746334/history","NAME":"Michigan","node_id":1746334,"version":2}}
,{"type":"Feature","geometry":{"type":"Point","coordinates":[-85.6975946,42.960741]},"properties":{"link":"https://navigator.er.usgs.gov/browse/node/1746064/history","NAME":"Michigan","node_id":1746064,"version":2}}
,{"type":"Feature","geometry":{"type":"Point","coordinates":[-85.7121598,42.973432]},"properties":{"link":"https://navigator.er.usgs.gov/browse/node/1744548/history","NAME":"Michigan","node_id":1744548,"version":2}}
,{"type":"Feature","geometry":{"type":"Point","coordinates":[-85.7289791,42.9746564]},"properties":{"link":"https://navigator.er.usgs.gov/browse/node/1738621/history","NAME":"Michigan","node_id":1738621,"version":2}}
,{"type":"Feature","geometry":{"type":"Point","coordinates":[-85.6857745,42.9900466]},"properties":{"link":"https://navigator.er.usgs.gov/browse/node/1737736/history","NAME":"Michigan","node_id":1737736,"version":2}}
,{"type":"Feature","geometry":{"type":"Point","coordinates":[-85.6857745,42.9898793]},"properties":{"link":"https://navigator.er.usgs.gov/browse/node/1734228/history","NAME":"Michigan","node_id":1734228,"version":2}}
,{"type":"Feature","geometry":{"type":"Point","coordinates":[-85.6115198,42.9417098]},"properties":{"link":"https://navigator.er.usgs.gov/browse/node/1732654/history","NAME":"Michigan","node_id":1732654,"version":2}}
,{"type":"Feature","geometry":{"type":"Point","coordinates":[-85.6211332,42.9350308]},"properties":{"link":"https://navigator.er.usgs.gov/browse/node/1724363/history","NAME":"Michigan","node_id":1724363,"version":2}}
,{"type":"Feature","geometry":{"type":"Point","coordinates":[-85.5955631,42.9273898]},"properties":{"link":"https://navigator.er.usgs.gov/browse/node/1714125/history","NAME":"Michigan","node_id":1714125,"version":2}}
,{"type":"Feature","geometry":{"type":"Point","coordinates":[-85.5876049,42.929963]},"properties":{"link":"https://navigator.er.usgs.gov/browse/node/1697338/history","NAME":"Michigan","node_id":1697338,"version":2}}
,{"type":"Feature","geometry":{"type":"Point","coordinates":[-85.5864143,42.9280151]},"properties":{"link":"https://navigator.er.usgs.gov/browse/node/1697039/history","NAME":"Michigan","node_id":1697039,"version":3}}
,{"type":"Feature","geometry":{"type":"Point","coordinates":[-85.5875483,42.9299158]},"properties":{"link":"https://navigator.er.usgs.gov/browse/node/1697039/history","NAME":"Michigan","node_id":1697039,"version":2}}
]}
