{"name":"NewFeatureType","type":"FeatureCollection"
,"features":[
{"type":"Feature","geometry":{"type":"Point","coordinates":[-117.4431581,47.698999]},"properties":{"link":"https://navigator.er.usgs.gov/browse/node/2093276/history","NAME":"Washington","node_id":2093276,"version":1}}
,{"type":"Feature","geometry":{"type":"Point","coordinates":[-117.4207436,47.784746]},"properties":{"link":"https://navigator.er.usgs.gov/browse/node/2093259/history","NAME":"Washington","node_id":2093259,"version":2}}
,{"type":"Feature","geometry":{"type":"Point","coordinates":[-117.4207436,47.784746]},"properties":{"link":"https://navigator.er.usgs.gov/browse/node/2093259/history","NAME":"Washington","node_id":2093259,"version":1}}
,{"type":"Feature","geometry":{"type":"Point","coordinates":[-104.8567322,39.7564056]},"properties":{"link":"https://navigator.er.usgs.gov/browse/node/2090424/history","NAME":"Colorado","node_id":2090424,"version":2}}
,{"type":"Feature","geometry":{"type":"Point","coordinates":[-117.2479348,47.6578804]},"properties":{"link":"https://navigator.er.usgs.gov/browse/node/2089090/history","NAME":"Washington","node_id":2089090,"version":2}}
,{"type":"Feature","geometry":{"type":"Point","coordinates":[-72.5128632,42.7621683]},"properties":{"link":"https://navigator.er.usgs.gov/browse/node/2075844/history","NAME":"Vermont","node_id":2075844,"version":2}}
,{"type":"Feature","geometry":{"type":"Point","coordinates":[-87.7560619,34.0251722]},"properties":{"link":"https://navigator.er.usgs.gov/browse/node/2063854/history","NAME":"Alabama","node_id":2063854,"version":2}}
,{"type":"Feature","geometry":{"type":"Point","coordinates":[-88.1417675,42.2600966]},"properties":{"link":"https://navigator.er.usgs.gov/browse/node/2063515/history","NAME":"Illinois","node_id":2063515,"version":2}}
,{"type":"Feature","geometry":{"type":"Point","coordinates":[-117.6831385,47.8972708]},"properties":{"link":"https://navigator.er.usgs.gov/browse/node/2062595/history","NAME":"Washington","node_id":2062595,"version":1}}
,{"type":"Feature","geometry":{"type":"Point","coordinates":[-104.6507728,45.3920122]},"properties":{"link":"https://navigator.er.usgs.gov/browse/node/2062585/history","NAME":"Montana","node_id":2062585,"version":2}}
,{"type":"Feature","geometry":{"type":"Point","coordinates":[-104.6507728,45.3920122]},"properties":{"link":"https://navigator.er.usgs.gov/browse/node/2062585/history","NAME":"Montana","node_id":2062585,"version":1}}
,{"type":"Feature","geometry":{"type":"Point","coordinates":[-117.7459662,48.0601339]},"properties":{"link":"https://navigator.er.usgs.gov/browse/node/2062568/history","NAME":"Washington","node_id":2062568,"version":1}}
,{"type":"Feature","geometry":{"type":"Point","coordinates":[-117.7461685,48.0595008]},"properties":{"link":"https://navigator.er.usgs.gov/browse/node/2062567/history","NAME":"Washington","node_id":2062567,"version":1}}
,{"type":"Feature","geometry":{"type":"Point","coordinates":[-72.5634036,42.8592102]},"properties":{"link":"https://navigator.er.usgs.gov/browse/node/2062457/history","NAME":"Vermont","node_id":2062457,"version":1}}
,{"type":"Feature","geometry":{"type":"Point","coordinates":[-72.5543766,42.8413953]},"properties":{"link":"https://navigator.er.usgs.gov/browse/node/2062442/history","NAME":"Vermont","node_id":2062442,"version":1}}
,{"type":"Feature","geometry":{"type":"Point","coordinates":[-72.5608565,42.8365259]},"properties":{"link":"https://navigator.er.usgs.gov/browse/node/2062441/history","NAME":"Vermont","node_id":2062441,"version":2}}
,{"type":"Feature","geometry":{"type":"Point","coordinates":[-72.5608565,42.8365259]},"properties":{"link":"https://navigator.er.usgs.gov/browse/node/2062441/history","NAME":"Vermont","node_id":2062441,"version":1}}
,{"type":"Feature","geometry":{"type":"Point","coordinates":[-117.2938911,48.016949]},"properties":{"link":"https://navigator.er.usgs.gov/browse/node/2062439/history","NAME":"Washington","node_id":2062439,"version":1}}
,{"type":"Feature","geometry":{"type":"Point","coordinates":[-117.425918,47.7163122]},"properties":{"link":"https://navigator.er.usgs.gov/browse/node/2059489/history","NAME":"Washington","node_id":2059489,"version":4}}
,{"type":"Feature","geometry":{"type":"Point","coordinates":[-117.425918,47.7163122]},"properties":{"link":"https://navigator.er.usgs.gov/browse/node/2059489/history","NAME":"Washington","node_id":2059489,"version":3}}
,{"type":"Feature","geometry":{"type":"Point","coordinates":[-117.425918,47.7163122]},"properties":{"link":"https://navigator.er.usgs.gov/browse/node/2059489/history","NAME":"Washington","node_id":2059489,"version":2}}
,{"type":"Feature","geometry":{"type":"Point","coordinates":[-70.5685723,41.612068]},"properties":{"link":"https://navigator.er.usgs.gov/browse/node/2043889/history","NAME":"Massachusetts","node_id":2043889,"version":3}}
,{"type":"Feature","geometry":{"type":"Point","coordinates":[-81.5075252,39.5298573]},"properties":{"link":"https://navigator.er.usgs.gov/browse/node/2038903/history","NAME":"Ohio","node_id":2038903,"version":3}}
,{"type":"Feature","geometry":{"type":"Point","coordinates":[-81.5062914,39.5295967]},"properties":{"link":"https://navigator.er.usgs.gov/browse/node/2038902/history","NAME":"Ohio","node_id":2038902,"version":3}}
,{"type":"Feature","geometry":{"type":"Point","coordinates":[-95.9981475,36.1578974]},"properties":{"link":"https://navigator.er.usgs.gov/browse/node/2038767/history","NAME":"Oklahoma","node_id":2038767,"version":2}}
,{"type":"Feature","geometry":{"type":"Point","coordinates":[-105.2612597,39.9917692]},"properties":{"link":"https://navigator.er.usgs.gov/browse/node/2038130/history","NAME":"Colorado","node_id":2038130,"version":3}}
,{"type":"Feature","geometry":{"type":"Point","coordinates":[-72.8646433,40.8655337]},"properties":{"link":"https://navigator.er.usgs.gov/browse/node/2038124/history","NAME":"New York","node_id":2038124,"version":2}}
,{"type":"Feature","geometry":{"type":"Point","coordinates":[-84.5677622,33.3603762]},"properties":{"link":"https://navigator.er.usgs.gov/browse/node/2038123/history","NAME":"Georgia","node_id":2038123,"version":2}}
,{"type":"Feature","geometry":{"type":"Point","coordinates":[-77.9128723,34.2762726]},"properties":{"link":"https://navigator.er.usgs.gov/browse/node/2038122/history","NAME":"North Carolina","node_id":2038122,"version":2}}
,{"type":"Feature","geometry":{"type":"Point","coordinates":[-76.8766073,34.7762956]},"properties":{"link":"https://navigator.er.usgs.gov/browse/node/2038121/history","NAME":"North Carolina","node_id":2038121,"version":2}}
,{"type":"Feature","geometry":{"type":"Point","coordinates":[-78.6390827,35.7805036]},"properties":{"link":"https://navigator.er.usgs.gov/browse/node/2028803/history","NAME":"North Carolina","node_id":2028803,"version":3}}
,{"type":"Feature","geometry":{"type":"Point","coordinates":[-77.855171,34.2484007]},"properties":{"link":"https://navigator.er.usgs.gov/browse/node/2028657/history","NAME":"North Carolina","node_id":2028657,"version":2}}
,{"type":"Feature","geometry":{"type":"Point","coordinates":[-77.9495246,34.235915]},"properties":{"link":"https://navigator.er.usgs.gov/browse/node/2023227/history","NAME":"North Carolina","node_id":2023227,"version":2}}
,{"type":"Feature","geometry":{"type":"Point","coordinates":[-96.1904174,38.4099627]},"properties":{"link":"https://navigator.er.usgs.gov/browse/node/2013344/history","NAME":"Kansas","node_id":2013344,"version":2}}
,{"type":"Feature","geometry":{"type":"Point","coordinates":[-92.7619379,37.1500426]},"properties":{"link":"https://navigator.er.usgs.gov/browse/node/2012143/history","NAME":"Missouri","node_id":2012143,"version":4}}
,{"type":"Feature","geometry":{"type":"Point","coordinates":[-92.7617555,37.148375]},"properties":{"link":"https://navigator.er.usgs.gov/browse/node/2012143/history","NAME":"Missouri","node_id":2012143,"version":3}}
,{"type":"Feature","geometry":{"type":"Point","coordinates":[-96.4300726,43.391418]},"properties":{"link":"https://navigator.er.usgs.gov/browse/node/2011433/history","NAME":"Iowa","node_id":2011433,"version":2}}
,{"type":"Feature","geometry":{"type":"Point","coordinates":[-96.264559,38.5084853]},"properties":{"link":"https://navigator.er.usgs.gov/browse/node/2009638/history","NAME":"Kansas","node_id":2009638,"version":2}}
,{"type":"Feature","geometry":{"type":"Point","coordinates":[-96.430441,43.3919243]},"properties":{"link":"https://navigator.er.usgs.gov/browse/node/2009110/history","NAME":"Iowa","node_id":2009110,"version":2}}
,{"type":"Feature","geometry":{"type":"Point","coordinates":[-96.1502521,38.6598997]},"properties":{"link":"https://navigator.er.usgs.gov/browse/node/2007102/history","NAME":"Kansas","node_id":2007102,"version":2}}
,{"type":"Feature","geometry":{"type":"Point","coordinates":[-85.880054,37.700034]},"properties":{"link":"https://navigator.er.usgs.gov/browse/node/2002715/history","NAME":"Kentucky","node_id":2002715,"version":2}}
,{"type":"Feature","geometry":{"type":"Point","coordinates":[-96.4282723,43.3054652]},"properties":{"link":"https://navigator.er.usgs.gov/browse/node/2000609/history","NAME":"Iowa","node_id":2000609,"version":2}}
,{"type":"Feature","geometry":{"type":"Point","coordinates":[-92.761281,37.1501422]},"properties":{"link":"https://navigator.er.usgs.gov/browse/node/1989013/history","NAME":"Missouri","node_id":1989013,"version":4}}
,{"type":"Feature","geometry":{"type":"Point","coordinates":[-96.4299697,43.3923804]},"properties":{"link":"https://navigator.er.usgs.gov/browse/node/1987803/history","NAME":"Iowa","node_id":1987803,"version":2}}
,{"type":"Feature","geometry":{"type":"Point","coordinates":[-85.882526,37.703008]},"properties":{"link":"https://navigator.er.usgs.gov/browse/node/1979409/history","NAME":"Kentucky","node_id":1979409,"version":2}}
,{"type":"Feature","geometry":{"type":"Point","coordinates":[-96.431052,43.3037424]},"properties":{"link":"https://navigator.er.usgs.gov/browse/node/1961683/history","NAME":"Iowa","node_id":1961683,"version":2}}
,{"type":"Feature","geometry":{"type":"Point","coordinates":[-95.5408644,29.9695553]},"properties":{"link":"https://navigator.er.usgs.gov/browse/node/1956922/history","NAME":"Texas","node_id":1956922,"version":2}}
,{"type":"Feature","geometry":{"type":"Point","coordinates":[-77.642956,38.654745]},"properties":{"link":"https://navigator.er.usgs.gov/browse/node/1956020/history","NAME":"Virginia","node_id":1956020,"version":3}}
,{"type":"Feature","geometry":{"type":"Point","coordinates":[-95.9960244,36.1541628]},"properties":{"link":"https://navigator.er.usgs.gov/browse/node/1945977/history","NAME":"Oklahoma","node_id":1945977,"version":4}}
,{"type":"Feature","geometry":{"type":"Point","coordinates":[-96.1818254,38.4059254]},"properties":{"link":"https://navigator.er.usgs.gov/browse/node/1938450/history","NAME":"Kansas","node_id":1938450,"version":3}}
,{"type":"Feature","geometry":{"type":"Point","coordinates":[-96.181871,38.405917]},"properties":{"link":"https://navigator.er.usgs.gov/browse/node/1938450/history","NAME":"Kansas","node_id":1938450,"version":2}}
,{"type":"Feature","geometry":{"type":"Point","coordinates":[-96.4322053,43.3081372]},"properties":{"link":"https://navigator.er.usgs.gov/browse/node/1933525/history","NAME":"Iowa","node_id":1933525,"version":2}}
,{"type":"Feature","geometry":{"type":"Point","coordinates":[-96.2959116,37.8214232]},"properties":{"link":"https://navigator.er.usgs.gov/browse/node/1930514/history","NAME":"Kansas","node_id":1930514,"version":2}}
,{"type":"Feature","geometry":{"type":"Point","coordinates":[-100.2051934,39.2331152]},"properties":{"link":"https://navigator.er.usgs.gov/browse/node/1917765/history","NAME":"Kansas","node_id":1917765,"version":2}}
,{"type":"Feature","geometry":{"type":"Point","coordinates":[-94.2121003,46.9866037]},"properties":{"link":"https://navigator.er.usgs.gov/browse/node/1900722/history","NAME":"Minnesota","node_id":1900722,"version":3}}
,{"type":"Feature","geometry":{"type":"Point","coordinates":[-78.4782708,38.0299511]},"properties":{"link":"https://navigator.er.usgs.gov/browse/node/1898995/history","NAME":"Virginia","node_id":1898995,"version":3}}
,{"type":"Feature","geometry":{"type":"Point","coordinates":[-72.6846294,41.7639439]},"properties":{"link":"https://navigator.er.usgs.gov/browse/node/1876535/history","NAME":"Connecticut","node_id":1876535,"version":2}}
,{"type":"Feature","geometry":{"type":"Point","coordinates":[-72.6821942,41.7641458]},"properties":{"link":"https://navigator.er.usgs.gov/browse/node/1876534/history","NAME":"Connecticut","node_id":1876534,"version":2}}
,{"type":"Feature","geometry":{"type":"Point","coordinates":[-72.573817,42.8421941]},"properties":{"link":"https://navigator.er.usgs.gov/browse/node/1875679/history","NAME":"Vermont","node_id":1875679,"version":2}}
,{"type":"Feature","geometry":{"type":"Point","coordinates":[-72.6225443,42.8006392]},"properties":{"link":"https://navigator.er.usgs.gov/browse/node/1874998/history","NAME":"Vermont","node_id":1874998,"version":2}}
,{"type":"Feature","geometry":{"type":"Point","coordinates":[-72.5650206,42.851759]},"properties":{"link":"https://navigator.er.usgs.gov/browse/node/1870081/history","NAME":"Vermont","node_id":1870081,"version":2}}
,{"type":"Feature","geometry":{"type":"Point","coordinates":[-72.5979923,42.8511093]},"properties":{"link":"https://navigator.er.usgs.gov/browse/node/1869467/history","NAME":"Vermont","node_id":1869467,"version":2}}
,{"type":"Feature","geometry":{"type":"Point","coordinates":[-72.5582432,42.8565269]},"properties":{"link":"https://navigator.er.usgs.gov/browse/node/1867265/history","NAME":"Vermont","node_id":1867265,"version":2}}
,{"type":"Feature","geometry":{"type":"Point","coordinates":[-72.5535581,42.836946]},"properties":{"link":"https://navigator.er.usgs.gov/browse/node/1867216/history","NAME":"Vermont","node_id":1867216,"version":2}}
,{"type":"Feature","geometry":{"type":"Point","coordinates":[-72.5624872,42.836089]},"properties":{"link":"https://navigator.er.usgs.gov/browse/node/1866261/history","NAME":"Vermont","node_id":1866261,"version":3}}
,{"type":"Feature","geometry":{"type":"Point","coordinates":[-72.5624872,42.836089]},"properties":{"link":"https://navigator.er.usgs.gov/browse/node/1866261/history","NAME":"Vermont","node_id":1866261,"version":2}}
,{"type":"Feature","geometry":{"type":"Point","coordinates":[-72.5185724,42.7760284]},"properties":{"link":"https://navigator.er.usgs.gov/browse/node/1864918/history","NAME":"Vermont","node_id":1864918,"version":2}}
,{"type":"Feature","geometry":{"type":"Point","coordinates":[-72.5579473,42.8401714]},"properties":{"link":"https://navigator.er.usgs.gov/browse/node/1861794/history","NAME":"Vermont","node_id":1861794,"version":2}}
,{"type":"Feature","geometry":{"type":"Point","coordinates":[-73.3480929,44.8846951]},"properties":{"link":"https://navigator.er.usgs.gov/browse/node/1861012/history","NAME":"Vermont","node_id":1861012,"version":2}}
,{"type":"Feature","geometry":{"type":"Point","coordinates":[-72.587809,42.83616]},"properties":{"link":"https://navigator.er.usgs.gov/browse/node/1855611/history","NAME":"Vermont","node_id":1855611,"version":2}}
,{"type":"Feature","geometry":{"type":"Point","coordinates":[-72.5611075,42.8356506]},"properties":{"link":"https://navigator.er.usgs.gov/browse/node/1853381/history","NAME":"Vermont","node_id":1853381,"version":3}}
,{"type":"Feature","geometry":{"type":"Point","coordinates":[-72.5611075,42.8356506]},"properties":{"link":"https://navigator.er.usgs.gov/browse/node/1853381/history","NAME":"Vermont","node_id":1853381,"version":2}}
,{"type":"Feature","geometry":{"type":"Point","coordinates":[-72.7686158,42.7842959]},"properties":{"link":"https://navigator.er.usgs.gov/browse/node/1851519/history","NAME":"Vermont","node_id":1851519,"version":2}}
,{"type":"Feature","geometry":{"type":"Point","coordinates":[-88.7986124,30.8746422]},"properties":{"link":"https://navigator.er.usgs.gov/browse/node/1846895/history","NAME":"Mississippi","node_id":1846895,"version":2}}
,{"type":"Feature","geometry":{"type":"Point","coordinates":[-72.5631564,42.8538588]},"properties":{"link":"https://navigator.er.usgs.gov/browse/node/1844583/history","NAME":"Vermont","node_id":1844583,"version":2}}
,{"type":"Feature","geometry":{"type":"Point","coordinates":[-72.5756116,42.8532939]},"properties":{"link":"https://navigator.er.usgs.gov/browse/node/1844414/history","NAME":"Vermont","node_id":1844414,"version":2}}
,{"type":"Feature","geometry":{"type":"Point","coordinates":[-72.5629054,42.8591995]},"properties":{"link":"https://navigator.er.usgs.gov/browse/node/1844391/history","NAME":"Vermont","node_id":1844391,"version":2}}
,{"type":"Feature","geometry":{"type":"Point","coordinates":[-72.6017224,42.8560377]},"properties":{"link":"https://navigator.er.usgs.gov/browse/node/1837429/history","NAME":"Vermont","node_id":1837429,"version":2}}
,{"type":"Feature","geometry":{"type":"Point","coordinates":[-72.7686792,42.9510142]},"properties":{"link":"https://navigator.er.usgs.gov/browse/node/1837417/history","NAME":"Vermont","node_id":1837417,"version":2}}
,{"type":"Feature","geometry":{"type":"Point","coordinates":[-72.8663867,42.9461118]},"properties":{"link":"https://navigator.er.usgs.gov/browse/node/1837349/history","NAME":"Vermont","node_id":1837349,"version":2}}
,{"type":"Feature","geometry":{"type":"Point","coordinates":[-72.7736092,42.786292]},"properties":{"link":"https://navigator.er.usgs.gov/browse/node/1835719/history","NAME":"Vermont","node_id":1835719,"version":2}}
,{"type":"Feature","geometry":{"type":"Point","coordinates":[-96.9203059,40.3947247]},"properties":{"link":"https://navigator.er.usgs.gov/browse/node/1835611/history","NAME":"Nebraska","node_id":1835611,"version":3}}
,{"type":"Feature","geometry":{"type":"Point","coordinates":[-72.5595281,42.8545106]},"properties":{"link":"https://navigator.er.usgs.gov/browse/node/1834804/history","NAME":"Vermont","node_id":1834804,"version":3}}
,{"type":"Feature","geometry":{"type":"Point","coordinates":[-72.5595281,42.8545106]},"properties":{"link":"https://navigator.er.usgs.gov/browse/node/1834804/history","NAME":"Vermont","node_id":1834804,"version":2}}
,{"type":"Feature","geometry":{"type":"Point","coordinates":[-71.5076226,45.008286]},"properties":{"link":"https://navigator.er.usgs.gov/browse/node/1834236/history","NAME":"Vermont","node_id":1834236,"version":2}}
,{"type":"Feature","geometry":{"type":"Point","coordinates":[-70.30381,41.70176]},"properties":{"link":"https://navigator.er.usgs.gov/browse/node/1831332/history","NAME":"Massachusetts","node_id":1831332,"version":2}}
,{"type":"Feature","geometry":{"type":"Point","coordinates":[-70.30711,41.69698]},"properties":{"link":"https://navigator.er.usgs.gov/browse/node/1831246/history","NAME":"Massachusetts","node_id":1831246,"version":2}}
,{"type":"Feature","geometry":{"type":"Point","coordinates":[-72.6202938,42.8669531]},"properties":{"link":"https://navigator.er.usgs.gov/browse/node/1830788/history","NAME":"Vermont","node_id":1830788,"version":2}}
,{"type":"Feature","geometry":{"type":"Point","coordinates":[-81.9055682,28.0474593]},"properties":{"link":"https://navigator.er.usgs.gov/browse/node/1830485/history","NAME":"Florida","node_id":1830485,"version":2}}
,{"type":"Feature","geometry":{"type":"Point","coordinates":[-80.0652852,26.784551]},"properties":{"link":"https://navigator.er.usgs.gov/browse/node/1829213/history","NAME":"Florida","node_id":1829213,"version":3}}
,{"type":"Feature","geometry":{"type":"Point","coordinates":[-72.8707803,42.8683818]},"properties":{"link":"https://navigator.er.usgs.gov/browse/node/1828962/history","NAME":"Vermont","node_id":1828962,"version":2}}
,{"type":"Feature","geometry":{"type":"Point","coordinates":[-72.5606367,42.8552826]},"properties":{"link":"https://navigator.er.usgs.gov/browse/node/1827985/history","NAME":"Vermont","node_id":1827985,"version":4}}
,{"type":"Feature","geometry":{"type":"Point","coordinates":[-72.5606367,42.8552826]},"properties":{"link":"https://navigator.er.usgs.gov/browse/node/1827985/history","NAME":"Vermont","node_id":1827985,"version":3}}
,{"type":"Feature","geometry":{"type":"Point","coordinates":[-72.5606367,42.8552826]},"properties":{"link":"https://navigator.er.usgs.gov/browse/node/1827985/history","NAME":"Vermont","node_id":1827985,"version":2}}
,{"type":"Feature","geometry":{"type":"Point","coordinates":[-72.0094573,44.4457253]},"properties":{"link":"https://navigator.er.usgs.gov/browse/node/1826284/history","NAME":"Vermont","node_id":1826284,"version":2}}
,{"type":"Feature","geometry":{"type":"Point","coordinates":[-80.1028783,26.1681388]},"properties":{"link":"https://navigator.er.usgs.gov/browse/node/1825255/history","NAME":"Florida","node_id":1825255,"version":2}}
,{"type":"Feature","geometry":{"type":"Point","coordinates":[-72.5607597,42.8516637]},"properties":{"link":"https://navigator.er.usgs.gov/browse/node/1823754/history","NAME":"Vermont","node_id":1823754,"version":2}}
,{"type":"Feature","geometry":{"type":"Point","coordinates":[-72.7702315,42.7858455]},"properties":{"link":"https://navigator.er.usgs.gov/browse/node/1821671/history","NAME":"Vermont","node_id":1821671,"version":2}}
,{"type":"Feature","geometry":{"type":"Point","coordinates":[-72.502917,42.7611834]},"properties":{"link":"https://navigator.er.usgs.gov/browse/node/1820454/history","NAME":"Vermont","node_id":1820454,"version":2}}
,{"type":"Feature","geometry":{"type":"Point","coordinates":[-90.5949272,41.4292942]},"properties":{"link":"https://navigator.er.usgs.gov/browse/node/1819229/history","NAME":"Illinois","node_id":1819229,"version":2}}
,{"type":"Feature","geometry":{"type":"Point","coordinates":[-72.5768893,42.8168583]},"properties":{"link":"https://navigator.er.usgs.gov/browse/node/1818073/history","NAME":"Vermont","node_id":1818073,"version":2}}
,{"type":"Feature","geometry":{"type":"Point","coordinates":[-90.5568802,41.494804]},"properties":{"link":"https://navigator.er.usgs.gov/browse/node/1817937/history","NAME":"Illinois","node_id":1817937,"version":2}}
,{"type":"Feature","geometry":{"type":"Point","coordinates":[-90.5862666,41.4794542]},"properties":{"link":"https://navigator.er.usgs.gov/browse/node/1816337/history","NAME":"Illinois","node_id":1816337,"version":2}}
,{"type":"Feature","geometry":{"type":"Point","coordinates":[-90.5806128,41.5070013]},"properties":{"link":"https://navigator.er.usgs.gov/browse/node/1816027/history","NAME":"Illinois","node_id":1816027,"version":2}}
,{"type":"Feature","geometry":{"type":"Point","coordinates":[-80.081416,26.7543263]},"properties":{"link":"https://navigator.er.usgs.gov/browse/node/1815375/history","NAME":"Florida","node_id":1815375,"version":3}}
,{"type":"Feature","geometry":{"type":"Point","coordinates":[-86.0571453,30.9437306]},"properties":{"link":"https://navigator.er.usgs.gov/browse/node/1815200/history","NAME":"Florida","node_id":1815200,"version":2}}
,{"type":"Feature","geometry":{"type":"Point","coordinates":[-85.4026776,30.950764]},"properties":{"link":"https://navigator.er.usgs.gov/browse/node/1813291/history","NAME":"Florida","node_id":1813291,"version":3}}
,{"type":"Feature","geometry":{"type":"Point","coordinates":[-72.56738,42.891035]},"properties":{"link":"https://navigator.er.usgs.gov/browse/node/1810980/history","NAME":"Vermont","node_id":1810980,"version":2}}
,{"type":"Feature","geometry":{"type":"Point","coordinates":[-72.5563601,42.8503232]},"properties":{"link":"https://navigator.er.usgs.gov/browse/node/1809856/history","NAME":"Vermont","node_id":1809856,"version":2}}
,{"type":"Feature","geometry":{"type":"Point","coordinates":[-72.7345994,42.838843]},"properties":{"link":"https://navigator.er.usgs.gov/browse/node/1809591/history","NAME":"Vermont","node_id":1809591,"version":2}}
,{"type":"Feature","geometry":{"type":"Point","coordinates":[-73.2030401,42.7127315]},"properties":{"link":"https://navigator.er.usgs.gov/browse/node/1809488/history","NAME":"Massachusetts","node_id":1809488,"version":2}}
,{"type":"Feature","geometry":{"type":"Point","coordinates":[-72.5125337,42.9772036]},"properties":{"link":"https://navigator.er.usgs.gov/browse/node/1809272/history","NAME":"Vermont","node_id":1809272,"version":3}}
,{"type":"Feature","geometry":{"type":"Point","coordinates":[-72.320267,42.9486496]},"properties":{"link":"https://navigator.er.usgs.gov/browse/node/1809210/history","NAME":"New Hampshire","node_id":1809210,"version":2}}
,{"type":"Feature","geometry":{"type":"Point","coordinates":[-90.524361,41.5132209]},"properties":{"link":"https://navigator.er.usgs.gov/browse/node/1808471/history","NAME":"Illinois","node_id":1808471,"version":2}}
,{"type":"Feature","geometry":{"type":"Point","coordinates":[-72.6517587,42.8259154]},"properties":{"link":"https://navigator.er.usgs.gov/browse/node/1808333/history","NAME":"Vermont","node_id":1808333,"version":2}}
,{"type":"Feature","geometry":{"type":"Point","coordinates":[-72.7434745,42.7914242]},"properties":{"link":"https://navigator.er.usgs.gov/browse/node/1808251/history","NAME":"Vermont","node_id":1808251,"version":2}}
,{"type":"Feature","geometry":{"type":"Point","coordinates":[-72.55907,42.8429452]},"properties":{"link":"https://navigator.er.usgs.gov/browse/node/1807288/history","NAME":"Vermont","node_id":1807288,"version":2}}
,{"type":"Feature","geometry":{"type":"Point","coordinates":[-72.6384829,42.753237]},"properties":{"link":"https://navigator.er.usgs.gov/browse/node/1806719/history","NAME":"Vermont","node_id":1806719,"version":2}}
,{"type":"Feature","geometry":{"type":"Point","coordinates":[-72.8014131,42.9479574]},"properties":{"link":"https://navigator.er.usgs.gov/browse/node/1805691/history","NAME":"Vermont","node_id":1805691,"version":2}}
,{"type":"Feature","geometry":{"type":"Point","coordinates":[-90.5339488,41.5175452]},"properties":{"link":"https://navigator.er.usgs.gov/browse/node/1800641/history","NAME":"Illinois","node_id":1800641,"version":2}}
,{"type":"Feature","geometry":{"type":"Point","coordinates":[-72.5537011,42.8434153]},"properties":{"link":"https://navigator.er.usgs.gov/browse/node/1796817/history","NAME":"Vermont","node_id":1796817,"version":2}}
,{"type":"Feature","geometry":{"type":"Point","coordinates":[-72.5645347,42.8581374]},"properties":{"link":"https://navigator.er.usgs.gov/browse/node/1793730/history","NAME":"Vermont","node_id":1793730,"version":2}}
,{"type":"Feature","geometry":{"type":"Point","coordinates":[-71.5368829,44.9973146]},"properties":{"link":"https://navigator.er.usgs.gov/browse/node/1791612/history","NAME":"Vermont","node_id":1791612,"version":2}}
,{"type":"Feature","geometry":{"type":"Point","coordinates":[-72.0116682,44.433136]},"properties":{"link":"https://navigator.er.usgs.gov/browse/node/1791081/history","NAME":"Vermont","node_id":1791081,"version":2}}
,{"type":"Feature","geometry":{"type":"Point","coordinates":[-72.5559234,42.846193]},"properties":{"link":"https://navigator.er.usgs.gov/browse/node/1788908/history","NAME":"Vermont","node_id":1788908,"version":2}}
,{"type":"Feature","geometry":{"type":"Point","coordinates":[-72.5934242,42.8631373]},"properties":{"link":"https://navigator.er.usgs.gov/browse/node/1787371/history","NAME":"Vermont","node_id":1787371,"version":2}}
,{"type":"Feature","geometry":{"type":"Point","coordinates":[-71.5553498,45.0059344]},"properties":{"link":"https://navigator.er.usgs.gov/browse/node/1785276/history","NAME":"Vermont","node_id":1785276,"version":2}}
,{"type":"Feature","geometry":{"type":"Point","coordinates":[-72.4837842,42.7538772]},"properties":{"link":"https://navigator.er.usgs.gov/browse/node/1784878/history","NAME":"Vermont","node_id":1784878,"version":3}}
,{"type":"Feature","geometry":{"type":"Point","coordinates":[-72.4839773,42.7539717]},"properties":{"link":"https://navigator.er.usgs.gov/browse/node/1784878/history","NAME":"Vermont","node_id":1784878,"version":2}}
,{"type":"Feature","geometry":{"type":"Point","coordinates":[-72.710599,42.9245544]},"properties":{"link":"https://navigator.er.usgs.gov/browse/node/1784798/history","NAME":"Vermont","node_id":1784798,"version":2}}
,{"type":"Feature","geometry":{"type":"Point","coordinates":[-89.7855716,32.6805485]},"properties":{"link":"https://navigator.er.usgs.gov/browse/node/1783020/history","NAME":"Mississippi","node_id":1783020,"version":5}}
,{"type":"Feature","geometry":{"type":"Point","coordinates":[-72.0199867,44.4300618]},"properties":{"link":"https://navigator.er.usgs.gov/browse/node/1781355/history","NAME":"Vermont","node_id":1781355,"version":2}}
,{"type":"Feature","geometry":{"type":"Point","coordinates":[-72.5537485,42.8406164]},"properties":{"link":"https://navigator.er.usgs.gov/browse/node/1780515/history","NAME":"Vermont","node_id":1780515,"version":2}}
,{"type":"Feature","geometry":{"type":"Point","coordinates":[-72.5661812,42.8375768]},"properties":{"link":"https://navigator.er.usgs.gov/browse/node/1772007/history","NAME":"Vermont","node_id":1772007,"version":3}}
,{"type":"Feature","geometry":{"type":"Point","coordinates":[-72.5605533,42.8537979]},"properties":{"link":"https://navigator.er.usgs.gov/browse/node/1771276/history","NAME":"Vermont","node_id":1771276,"version":2}}
,{"type":"Feature","geometry":{"type":"Point","coordinates":[-72.0066127,44.4451217]},"properties":{"link":"https://navigator.er.usgs.gov/browse/node/1771063/history","NAME":"Vermont","node_id":1771063,"version":2}}
,{"type":"Feature","geometry":{"type":"Point","coordinates":[-117.6305632,48.0634929]},"properties":{"link":"https://navigator.er.usgs.gov/browse/node/1770009/history","NAME":"Washington","node_id":1770009,"version":3}}
,{"type":"Feature","geometry":{"type":"Point","coordinates":[-117.6305632,48.0634929]},"properties":{"link":"https://navigator.er.usgs.gov/browse/node/1770009/history","NAME":"Washington","node_id":1770009,"version":2}}
,{"type":"Feature","geometry":{"type":"Point","coordinates":[-117.404446,47.653382]},"properties":{"link":"https://navigator.er.usgs.gov/browse/node/1769753/history","NAME":"Washington","node_id":1769753,"version":3}}
,{"type":"Feature","geometry":{"type":"Point","coordinates":[-117.6313614,48.0649819]},"properties":{"link":"https://navigator.er.usgs.gov/browse/node/1766594/history","NAME":"Washington","node_id":1766594,"version":2}}
,{"type":"Feature","geometry":{"type":"Point","coordinates":[-117.4341143,47.7095264]},"properties":{"link":"https://navigator.er.usgs.gov/browse/node/1766398/history","NAME":"Washington","node_id":1766398,"version":3}}
,{"type":"Feature","geometry":{"type":"Point","coordinates":[-117.4213616,47.6570134]},"properties":{"link":"https://navigator.er.usgs.gov/browse/node/1763281/history","NAME":"Washington","node_id":1763281,"version":4}}
,{"type":"Feature","geometry":{"type":"Point","coordinates":[-117.4241436,47.72292]},"properties":{"link":"https://navigator.er.usgs.gov/browse/node/1763132/history","NAME":"Washington","node_id":1763132,"version":3}}
,{"type":"Feature","geometry":{"type":"Point","coordinates":[-104.5518163,45.8906585]},"properties":{"link":"https://navigator.er.usgs.gov/browse/node/1761358/history","NAME":"Montana","node_id":1761358,"version":3}}
,{"type":"Feature","geometry":{"type":"Point","coordinates":[-104.5518163,45.8905689]},"properties":{"link":"https://navigator.er.usgs.gov/browse/node/1761358/history","NAME":"Montana","node_id":1761358,"version":2}}
,{"type":"Feature","geometry":{"type":"Point","coordinates":[-117.4335464,47.7209464]},"properties":{"link":"https://navigator.er.usgs.gov/browse/node/1760832/history","NAME":"Washington","node_id":1760832,"version":3}}
,{"type":"Feature","geometry":{"type":"Point","coordinates":[-117.36773,47.6557935]},"properties":{"link":"https://navigator.er.usgs.gov/browse/node/1760612/history","NAME":"Washington","node_id":1760612,"version":3}}
,{"type":"Feature","geometry":{"type":"Point","coordinates":[-104.551,45.88992]},"properties":{"link":"https://navigator.er.usgs.gov/browse/node/1759196/history","NAME":"Montana","node_id":1759196,"version":2}}
,{"type":"Feature","geometry":{"type":"Point","coordinates":[-80.0312057,40.5662234]},"properties":{"link":"https://navigator.er.usgs.gov/browse/node/1756752/history","NAME":"Pennsylvania","node_id":1756752,"version":4}}
,{"type":"Feature","geometry":{"type":"Point","coordinates":[-117.7404034,48.0593344]},"properties":{"link":"https://navigator.er.usgs.gov/browse/node/1752481/history","NAME":"Washington","node_id":1752481,"version":3}}
,{"type":"Feature","geometry":{"type":"Point","coordinates":[-117.7421849,48.0598765]},"properties":{"link":"https://navigator.er.usgs.gov/browse/node/1752481/history","NAME":"Washington","node_id":1752481,"version":2}}
,{"type":"Feature","geometry":{"type":"Point","coordinates":[-117.4371418,47.6984473]},"properties":{"link":"https://navigator.er.usgs.gov/browse/node/1751727/history","NAME":"Washington","node_id":1751727,"version":4}}
,{"type":"Feature","geometry":{"type":"Point","coordinates":[-117.4004521,47.6720163]},"properties":{"link":"https://navigator.er.usgs.gov/browse/node/1750960/history","NAME":"Washington","node_id":1750960,"version":3}}
,{"type":"Feature","geometry":{"type":"Point","coordinates":[-117.446394,47.6978854]},"properties":{"link":"https://navigator.er.usgs.gov/browse/node/1750147/history","NAME":"Washington","node_id":1750147,"version":4}}
,{"type":"Feature","geometry":{"type":"Point","coordinates":[-117.4149978,47.6772574]},"properties":{"link":"https://navigator.er.usgs.gov/browse/node/1750052/history","NAME":"Washington","node_id":1750052,"version":3}}
,{"type":"Feature","geometry":{"type":"Point","coordinates":[-117.7460916,48.0598268]},"properties":{"link":"https://navigator.er.usgs.gov/browse/node/1746658/history","NAME":"Washington","node_id":1746658,"version":2}}
,{"type":"Feature","geometry":{"type":"Point","coordinates":[-117.4512182,47.6989651]},"properties":{"link":"https://navigator.er.usgs.gov/browse/node/1744439/history","NAME":"Washington","node_id":1744439,"version":3}}
,{"type":"Feature","geometry":{"type":"Point","coordinates":[-117.4331666,47.652852]},"properties":{"link":"https://navigator.er.usgs.gov/browse/node/1741892/history","NAME":"Washington","node_id":1741892,"version":4}}
,{"type":"Feature","geometry":{"type":"Point","coordinates":[-104.4130057,45.0208293]},"properties":{"link":"https://navigator.er.usgs.gov/browse/node/1741730/history","NAME":"Montana","node_id":1741730,"version":2}}
,{"type":"Feature","geometry":{"type":"Point","coordinates":[-117.5887824,47.6453248]},"properties":{"link":"https://navigator.er.usgs.gov/browse/node/1735803/history","NAME":"Washington","node_id":1735803,"version":4}}
,{"type":"Feature","geometry":{"type":"Point","coordinates":[-117.419691,47.6723935]},"properties":{"link":"https://navigator.er.usgs.gov/browse/node/1735748/history","NAME":"Washington","node_id":1735748,"version":3}}
,{"type":"Feature","geometry":{"type":"Point","coordinates":[-117.3554357,47.6523717]},"properties":{"link":"https://navigator.er.usgs.gov/browse/node/1735174/history","NAME":"Washington","node_id":1735174,"version":3}}
,{"type":"Feature","geometry":{"type":"Point","coordinates":[-104.5499487,45.8883714]},"properties":{"link":"https://navigator.er.usgs.gov/browse/node/1733892/history","NAME":"Montana","node_id":1733892,"version":2}}
,{"type":"Feature","geometry":{"type":"Point","coordinates":[-117.3847586,47.6713609]},"properties":{"link":"https://navigator.er.usgs.gov/browse/node/1732646/history","NAME":"Washington","node_id":1732646,"version":3}}
,{"type":"Feature","geometry":{"type":"Point","coordinates":[-117.4202727,47.6519278]},"properties":{"link":"https://navigator.er.usgs.gov/browse/node/1732433/history","NAME":"Washington","node_id":1732433,"version":4}}
,{"type":"Feature","geometry":{"type":"Point","coordinates":[-117.4200188,47.6980686]},"properties":{"link":"https://navigator.er.usgs.gov/browse/node/1731790/history","NAME":"Washington","node_id":1731790,"version":3}}
,{"type":"Feature","geometry":{"type":"Point","coordinates":[-117.5766681,47.6541089]},"properties":{"link":"https://navigator.er.usgs.gov/browse/node/1731673/history","NAME":"Washington","node_id":1731673,"version":3}}
,{"type":"Feature","geometry":{"type":"Point","coordinates":[-105.0308579,45.2691916]},"properties":{"link":"https://navigator.er.usgs.gov/browse/node/1730802/history","NAME":"Montana","node_id":1730802,"version":5}}
,{"type":"Feature","geometry":{"type":"Point","coordinates":[-104.9166761,45.22502]},"properties":{"link":"https://navigator.er.usgs.gov/browse/node/1727565/history","NAME":"Montana","node_id":1727565,"version":4}}
,{"type":"Feature","geometry":{"type":"Point","coordinates":[-117.370814,48.8620764]},"properties":{"link":"https://navigator.er.usgs.gov/browse/node/1726664/history","NAME":"Washington","node_id":1726664,"version":2}}
,{"type":"Feature","geometry":{"type":"Point","coordinates":[-117.4776354,47.7024613]},"properties":{"link":"https://navigator.er.usgs.gov/browse/node/1725437/history","NAME":"Washington","node_id":1725437,"version":4}}
,{"type":"Feature","geometry":{"type":"Point","coordinates":[-117.408539,47.6502768]},"properties":{"link":"https://navigator.er.usgs.gov/browse/node/1724076/history","NAME":"Washington","node_id":1724076,"version":4}}
,{"type":"Feature","geometry":{"type":"Point","coordinates":[-117.408539,47.6502768]},"properties":{"link":"https://navigator.er.usgs.gov/browse/node/1724076/history","NAME":"Washington","node_id":1724076,"version":3}}
,{"type":"Feature","geometry":{"type":"Point","coordinates":[-117.413078,47.6491478]},"properties":{"link":"https://navigator.er.usgs.gov/browse/node/1723786/history","NAME":"Washington","node_id":1723786,"version":3}}
,{"type":"Feature","geometry":{"type":"Point","coordinates":[-117.4072578,47.6497446]},"properties":{"link":"https://navigator.er.usgs.gov/browse/node/1723735/history","NAME":"Washington","node_id":1723735,"version":3}}
,{"type":"Feature","geometry":{"type":"Point","coordinates":[-115.3486535,47.5940678]},"properties":{"link":"https://navigator.er.usgs.gov/browse/node/1721470/history","NAME":"Montana","node_id":1721470,"version":2}}
,{"type":"Feature","geometry":{"type":"Point","coordinates":[-117.4289294,47.6656115]},"properties":{"link":"https://navigator.er.usgs.gov/browse/node/1720307/history","NAME":"Washington","node_id":1720307,"version":4}}
,{"type":"Feature","geometry":{"type":"Point","coordinates":[-117.5955661,47.6435675]},"properties":{"link":"https://navigator.er.usgs.gov/browse/node/1718306/history","NAME":"Washington","node_id":1718306,"version":3}}
,{"type":"Feature","geometry":{"type":"Point","coordinates":[-117.5764534,47.6469918]},"properties":{"link":"https://navigator.er.usgs.gov/browse/node/1712225/history","NAME":"Washington","node_id":1712225,"version":3}}
,{"type":"Feature","geometry":{"type":"Point","coordinates":[-117.5934866,47.6444387]},"properties":{"link":"https://navigator.er.usgs.gov/browse/node/1704249/history","NAME":"Washington","node_id":1704249,"version":3}}
,{"type":"Feature","geometry":{"type":"Point","coordinates":[-117.4761518,47.7069513]},"properties":{"link":"https://navigator.er.usgs.gov/browse/node/1702642/history","NAME":"Washington","node_id":1702642,"version":3}}
,{"type":"Feature","geometry":{"type":"Point","coordinates":[-76.4423912,39.2368742]},"properties":{"link":"https://navigator.er.usgs.gov/browse/node/1701764/history","NAME":"Maryland","node_id":1701764,"version":2}}
,{"type":"Feature","geometry":{"type":"Point","coordinates":[-83.6298,41.6017]},"properties":{"link":"https://navigator.er.usgs.gov/browse/node/1698792/history","NAME":"Ohio","node_id":1698792,"version":3}}
,{"type":"Feature","geometry":{"type":"Point","coordinates":[-113.0699057,37.6641469]},"properties":{"link":"https://navigator.er.usgs.gov/browse/node/1698760/history","NAME":"Utah","node_id":1698760,"version":2}}
,{"type":"Feature","geometry":{"type":"Point","coordinates":[-83.1760455,41.1145636]},"properties":{"link":"https://navigator.er.usgs.gov/browse/node/1698751/history","NAME":"Ohio","node_id":1698751,"version":3}}
,{"type":"Feature","geometry":{"type":"Point","coordinates":[-117.2871251,47.6723986]},"properties":{"link":"https://navigator.er.usgs.gov/browse/node/1698590/history","NAME":"Washington","node_id":1698590,"version":4}}
,{"type":"Feature","geometry":{"type":"Point","coordinates":[-111.865553,40.6182393]},"properties":{"link":"https://navigator.er.usgs.gov/browse/node/1698588/history","NAME":"Utah","node_id":1698588,"version":3}}
,{"type":"Feature","geometry":{"type":"Point","coordinates":[-113.5874483,37.0921289]},"properties":{"link":"https://navigator.er.usgs.gov/browse/node/1698461/history","NAME":"Utah","node_id":1698461,"version":2}}
,{"type":"Feature","geometry":{"type":"Point","coordinates":[-111.985892,40.670671]},"properties":{"link":"https://navigator.er.usgs.gov/browse/node/1698460/history","NAME":"Utah","node_id":1698460,"version":2}}
,{"type":"Feature","geometry":{"type":"Point","coordinates":[-111.6422005,40.2406166]},"properties":{"link":"https://navigator.er.usgs.gov/browse/node/1698236/history","NAME":"Utah","node_id":1698236,"version":3}}
,{"type":"Feature","geometry":{"type":"Point","coordinates":[-118.3301596,46.0713496]},"properties":{"link":"https://navigator.er.usgs.gov/browse/node/1698173/history","NAME":"Washington","node_id":1698173,"version":4}}
,{"type":"Feature","geometry":{"type":"Point","coordinates":[-111.8358638,40.6666821]},"properties":{"link":"https://navigator.er.usgs.gov/browse/node/1698139/history","NAME":"Utah","node_id":1698139,"version":2}}
,{"type":"Feature","geometry":{"type":"Point","coordinates":[-83.675847,41.5833973]},"properties":{"link":"https://navigator.er.usgs.gov/browse/node/1698123/history","NAME":"Ohio","node_id":1698123,"version":3}}
,{"type":"Feature","geometry":{"type":"Point","coordinates":[-83.5655545,41.7077818]},"properties":{"link":"https://navigator.er.usgs.gov/browse/node/1697881/history","NAME":"Ohio","node_id":1697881,"version":4}}
,{"type":"Feature","geometry":{"type":"Point","coordinates":[-83.620437,41.545211]},"properties":{"link":"https://navigator.er.usgs.gov/browse/node/1697829/history","NAME":"Ohio","node_id":1697829,"version":5}}
,{"type":"Feature","geometry":{"type":"Point","coordinates":[-113.5628696,37.1084869]},"properties":{"link":"https://navigator.er.usgs.gov/browse/node/1697542/history","NAME":"Utah","node_id":1697542,"version":2}}
,{"type":"Feature","geometry":{"type":"Point","coordinates":[-109.9771,40.3002045]},"properties":{"link":"https://navigator.er.usgs.gov/browse/node/1697479/history","NAME":"Utah","node_id":1697479,"version":2}}
,{"type":"Feature","geometry":{"type":"Point","coordinates":[-83.6103547,41.692315]},"properties":{"link":"https://navigator.er.usgs.gov/browse/node/1697459/history","NAME":"Ohio","node_id":1697459,"version":4}}
,{"type":"Feature","geometry":{"type":"Point","coordinates":[-111.8944433,40.5876449]},"properties":{"link":"https://navigator.er.usgs.gov/browse/node/1697439/history","NAME":"Utah","node_id":1697439,"version":2}}
,{"type":"Feature","geometry":{"type":"Point","coordinates":[-117.4198468,47.6547142]},"properties":{"link":"https://navigator.er.usgs.gov/browse/node/1697268/history","NAME":"Washington","node_id":1697268,"version":4}}
,{"type":"Feature","geometry":{"type":"Point","coordinates":[-111.9006218,40.7218931]},"properties":{"link":"https://navigator.er.usgs.gov/browse/node/1697109/history","NAME":"Utah","node_id":1697109,"version":3}}
,{"type":"Feature","geometry":{"type":"Point","coordinates":[-111.6533307,40.1203821]},"properties":{"link":"https://navigator.er.usgs.gov/browse/node/1697078/history","NAME":"Utah","node_id":1697078,"version":4}}
,{"type":"Feature","geometry":{"type":"Point","coordinates":[-83.147535,39.98502]},"properties":{"link":"https://navigator.er.usgs.gov/browse/node/1697049/history","NAME":"Ohio","node_id":1697049,"version":2}}
,{"type":"Feature","geometry":{"type":"Point","coordinates":[-117.4180775,47.753699]},"properties":{"link":"https://navigator.er.usgs.gov/browse/node/1696985/history","NAME":"Washington","node_id":1696985,"version":5}}
,{"type":"Feature","geometry":{"type":"Point","coordinates":[-83.4695399,41.6383264]},"properties":{"link":"https://navigator.er.usgs.gov/browse/node/1696978/history","NAME":"Ohio","node_id":1696978,"version":3}}
,{"type":"Feature","geometry":{"type":"Point","coordinates":[-82.996903,39.964155]},"properties":{"link":"https://navigator.er.usgs.gov/browse/node/1696957/history","NAME":"Ohio","node_id":1696957,"version":3}}
,{"type":"Feature","geometry":{"type":"Point","coordinates":[-111.8884467,40.6448774]},"properties":{"link":"https://navigator.er.usgs.gov/browse/node/1696956/history","NAME":"Utah","node_id":1696956,"version":2}}
,{"type":"Feature","geometry":{"type":"Point","coordinates":[-117.2697544,47.6758885]},"properties":{"link":"https://navigator.er.usgs.gov/browse/node/1696870/history","NAME":"Washington","node_id":1696870,"version":4}}
,{"type":"Feature","geometry":{"type":"Point","coordinates":[-111.7134152,40.3355452]},"properties":{"link":"https://navigator.er.usgs.gov/browse/node/1696712/history","NAME":"Utah","node_id":1696712,"version":3}}
,{"type":"Feature","geometry":{"type":"Point","coordinates":[-117.9858029,47.8859955]},"properties":{"link":"https://navigator.er.usgs.gov/browse/node/1689830/history","NAME":"Washington","node_id":1689830,"version":2}}
,{"type":"Feature","geometry":{"type":"Point","coordinates":[-105.0032578,45.3069393]},"properties":{"link":"https://navigator.er.usgs.gov/browse/node/1689606/history","NAME":"Montana","node_id":1689606,"version":2}}
,{"type":"Feature","geometry":{"type":"Point","coordinates":[-117.6867243,47.8952961]},"properties":{"link":"https://navigator.er.usgs.gov/browse/node/1677774/history","NAME":"Washington","node_id":1677774,"version":5}}
,{"type":"Feature","geometry":{"type":"Point","coordinates":[-117.6867243,47.8952961]},"properties":{"link":"https://navigator.er.usgs.gov/browse/node/1677774/history","NAME":"Washington","node_id":1677774,"version":4}}
,{"type":"Feature","geometry":{"type":"Point","coordinates":[-117.385102,48.8419094]},"properties":{"link":"https://navigator.er.usgs.gov/browse/node/1676450/history","NAME":"Washington","node_id":1676450,"version":2}}
,{"type":"Feature","geometry":{"type":"Point","coordinates":[-117.4802076,47.6822199]},"properties":{"link":"https://navigator.er.usgs.gov/browse/node/1671406/history","NAME":"Washington","node_id":1671406,"version":4}}
,{"type":"Feature","geometry":{"type":"Point","coordinates":[-117.7141982,48.2586736]},"properties":{"link":"https://navigator.er.usgs.gov/browse/node/1669958/history","NAME":"Washington","node_id":1669958,"version":3}}
,{"type":"Feature","geometry":{"type":"Point","coordinates":[-115.3268552,47.595941]},"properties":{"link":"https://navigator.er.usgs.gov/browse/node/1666466/history","NAME":"Montana","node_id":1666466,"version":2}}
,{"type":"Feature","geometry":{"type":"Point","coordinates":[-117.4258722,47.6689359]},"properties":{"link":"https://navigator.er.usgs.gov/browse/node/1659285/history","NAME":"Washington","node_id":1659285,"version":3}}
]}
